impact_stack/observability/__init__.py
impact_stack/observability/health/__init__.py
impact_stack/observability/health/blueprint.py
impact_stack/observability/health/checks.py
impact_stack/observability/health/extension.py
impact_stack/observability/tracing/__init__.py
impact_stack/observability/tracing/celery.py
impact_stack/observability/tracing/extension.py
impact_stack/observability/tracing/gunicorn.py
impact_stack/observability/tracing/utils.py
impact_stack_observability-0.3.0.dist-info/licenses/LICENSE
impact_stack_observability-0.3.0.dist-info/METADATA
impact_stack_observability-0.3.0.dist-info/WHEEL
impact_stack_observability-0.3.0.dist-info/top_level.txt
impact_stack_observability-0.3.0.dist-info/RECORD
