Metadata-Version: 2.4
Name: impact-stack-observability
Version: 0.3.0
Summary: Observability for Impact Stack
Author-email: Alex Berger <alex@more-onion.com>
License:                     GNU GENERAL PUBLIC LICENSE
Platform: UNKNOWN
Classifier: Development Status :: 4 - Beta
Classifier: Framework :: Flask
Classifier: Intended Audience :: Developers
Classifier: License :: OSI Approved :: GNU General Public License v3 (GPLv3)
Classifier: License :: OSI Approved :: MIT License
Classifier: Programming Language :: Python :: 3
Classifier: Programming Language :: Python
Classifier: Topic :: Software Development
Requires-Python: >=3.11
License-File: LICENSE
Requires-Dist: flask
Requires-Dist: requests
Requires-Dist: opentelemetry-api>=1.35.0
Requires-Dist: opentelemetry-sdk>=1.35.0
Provides-Extra: dev
Requires-Dist: black; extra == "dev"
Requires-Dist: celery[redis]; extra == "dev"
Requires-Dist: flask-sqlalchemy; extra == "dev"
Requires-Dist: isort; extra == "dev"
Requires-Dist: pre-commit; extra == "dev"
Requires-Dist: pydocstyle[toml]>=6; extra == "dev"
Requires-Dist: pylint; extra == "dev"
Requires-Dist: pytest; extra == "dev"
Requires-Dist: pytest-cov; extra == "dev"
Requires-Dist: pytest-flask; extra == "dev"
Provides-Extra: celery
Requires-Dist: opentelemetry-instrumentation-celery>=0.56b0; extra == "celery"
Provides-Extra: flask
Requires-Dist: opentelemetry-instrumentation-flask>=0.56b0; extra == "flask"
Provides-Extra: logging
Requires-Dist: opentelemetry-instrumentation-logging>=0.56b0; extra == "logging"
Provides-Extra: requests
Requires-Dist: opentelemetry-instrumentation-requests>=0.56b0; extra == "requests"
Provides-Extra: sqlalchemy
Requires-Dist: opentelemetry-instrumentation-sqlalchemy>=0.56b0; extra == "sqlalchemy"
Dynamic: license-file
